patchpal/__init__.py
patchpal/agent.py
patchpal/cli.py
patchpal/context.py
patchpal/permissions.py
patchpal/skills.py
patchpal/system_prompt.md
patchpal/tool_schema.py
patchpal/tools.py
patchpal-0.7.0.dist-info/licenses/LICENSE
patchpal-0.7.0.dist-info/METADATA
patchpal-0.7.0.dist-info/WHEEL
patchpal-0.7.0.dist-info/entry_points.txt
patchpal-0.7.0.dist-info/top_level.txt
patchpal-0.7.0.dist-info/RECORD
