Metadata-Version: 2.4
Name: patchpal
Version: 0.7.0
Summary: A lean Claude Code clone in pure  Python
Author: PatchPal Contributors
License-Expression: Apache-2.0
Project-URL: Homepage, https://github.com/amaiya/patchpal
Project-URL: Repository, https://github.com/amaiya/patchpal
Project-URL: Issues, https://github.com/amaiya/patchpal/issues
Classifier: Development Status :: 3 - Alpha
Classifier: Intended Audience :: Developers
Classifier: Programming Language :: Python :: 3
Classifier: Programming Language :: Python :: 3.10
Classifier: Programming Language :: Python :: 3.11
Classifier: Programming Language :: Python :: 3.12
Classifier: Programming Language :: Python :: 3.13
Classifier: Topic :: Software Development :: Libraries :: Python Modules
Classifier: Topic :: Scientific/Engineering :: Artificial Intelligence
Requires-Python: >=3.10
License-File: LICENSE
Requires-Dist: litellm>=1.0.0
Requires-Dist: requests>=2.31.0
Requires-Dist: beautifulsoup4>=4.12.0
Requires-Dist: ddgs>=1.0.0
Requires-Dist: rich>=13.0.0
Requires-Dist: pyyaml>=6.0.0
Requires-Dist: prompt_toolkit>=3.0.0
Requires-Dist: tiktoken>=0.5.0
Requires-Dist: boto3
Provides-Extra: dev
Requires-Dist: pytest>=7.0.0; extra == "dev"
Requires-Dist: pytest-cov>=4.0.0; extra == "dev"
Requires-Dist: ruff==0.14.13; extra == "dev"
Requires-Dist: pre-commit>=3.0.0; extra == "dev"
Dynamic: license-file
